MANIFEST.in
setup.py
AnimePFP/AnimePFP.py
AnimePFP/__init__.py
AnimePFP.egg-info/PKG-INFO
AnimePFP.egg-info/SOURCES.txt
AnimePFP.egg-info/dependency_links.txt
AnimePFP.egg-info/top_level.txt