Metadata-Version: 2.1
Name: AnimePFP
Version: 1.0.4
Summary: Anime profile picture downloader using https://avatars.alphacoders.com/by_category/3
Home-page: https://github.com/LUA9/AnimePFPGenerator
Author: LUA9
Maintainer: LUA9
License: UNKNOWN
Platform: UNKNOWN
Requires: aiohttp
Requires: pyppeteer
Requires: bs4
Requires: tqdm
